ripple_energy/__init__.py
ripple_energy/constants.py
ripple_energy/exceptions.py
ripple_energy/helpers.py
ripple_energy/models.py
ripple_energy/ripple_energy.py
ripple_energy/graphql_client/__init__.py
ripple_energy/graphql_client/active_coop_status.py
ripple_energy/graphql_client/all_coops.py
ripple_energy/graphql_client/async_base_client.py
ripple_energy/graphql_client/authenticate.py
ripple_energy/graphql_client/base_model.py
ripple_energy/graphql_client/client.py
ripple_energy/graphql_client/consumption.py
ripple_energy/graphql_client/coop.py
ripple_energy/graphql_client/coop_timeline_progression.py
ripple_energy/graphql_client/cumulative_savings.py
ripple_energy/graphql_client/deauthenticate.py
ripple_energy/graphql_client/enums.py
ripple_energy/graphql_client/exceptions.py
ripple_energy/graphql_client/faqs.py
ripple_energy/graphql_client/fragments.py
ripple_energy/graphql_client/get_coop_timeline_progression.py
ripple_energy/graphql_client/get_insights_chart_data.py
ripple_energy/graphql_client/input_types.py
ripple_energy/graphql_client/insights_chart_data.py
ripple_energy/graphql_client/me.py
ripple_energy/graphql_client/member.py
ripple_energy/graphql_client/monthly_savings.py
ripple_energy/graphql_client/refresh_token.py
ripple_energy/graphql_client/tribe_url.py
ripple_energy/graphql_client/verify.py
ripple_energy/graphql_client/verify_token.py
ripple_energy/graphql_client/version.py
ripple_energy/graphql_client/wind_farm_generation.py
ripple_energy/graphql_client/wind_farm_generation_data.py
ripple_energy/graphql_queries/README.md
ripple_energy/graphql_queries/custom_fragments/consumption.graphql
ripple_energy/graphql_queries/custom_fragments/coop.graphql
ripple_energy/graphql_queries/custom_fragments/member.graphql
ripple_energy/graphql_queries/custom_fragments/waiting_list.graphql
ripple_energy/graphql_queries/custom_fragments/waiting_list_place.graphql
ripple_energy/graphql_queries/custom_mutations/deauthenticate.graphql
ripple_energy-3.0.3.dist-info/METADATA
ripple_energy-3.0.3.dist-info/WHEEL
ripple_energy-3.0.3.dist-info/licenses/LICENSE.txt
ripple_energy-3.0.3.dist-info/RECORD
