Metadata-Version: 2.3
Name: ripple-energy
Version: 3.0.3
Summary: Python Module For Ripple Energy
Project-URL: Documentation, https://github.com/danieledwardgeorgehitchcock/ripple-energy#readme
Project-URL: Issues, https://github.com/danieledwardgeorgehitchcock/ripple-energy/issues
Project-URL: Source, https://github.com/danieledwardgeorgehitchcock/ripple-energy
Author-email: Daniel Hitchcock <daniel.edward.george.hitchcock@gmail.com>
License-Expression: MIT
License-File: LICENSE.txt
Classifier: Development Status :: 4 - Beta
Classifier: Programming Language :: Python
Classifier: Programming Language :: Python :: 3.7
Classifier: Programming Language :: Python :: 3.8
Classifier: Programming Language :: Python :: 3.9
Classifier: Programming Language :: Python :: 3.10
Classifier: Programming Language :: Python :: 3.11
Classifier: Programming Language :: Python :: Implementation :: CPython
Classifier: Programming Language :: Python :: Implementation :: PyPy
Requires-Python: >=3.7
Requires-Dist: ariadne-codegen~=0.9.0
